libpymath/__init__.py
libpymath/error.cpython-37m-darwin.so
libpymath/core/matrix.cpython-37m-darwin.so
libpymath/matrix/__init__.py
libpymath/matrix/_threadInfo.py
libpymath/matrix/_threadSetup.py
libpymath/matrix/matrix.py
libpymath/network/__init__.py
libpymath/network/network.py
libpymath/progress/__init__.py
libpymath/progress/progress.py
libpymath/src/__init__.py
libpymath/src/error/__init__.py
libpymath/src/matrix/__init__.py
libpymath-0.6.1.dist-info/LICENSE.txt
libpymath-0.6.1.dist-info/METADATA
libpymath-0.6.1.dist-info/WHEEL
libpymath-0.6.1.dist-info/top_level.txt
libpymath-0.6.1.dist-info/RECORD
