Metadata-Version: 2.1
Name: libpymath
Version: 0.6.1
Summary: A general purpose Python math module
Home-page: https://www.github.com/pencilcaseman/libpymath
Author: Toby Davis
Author-email: pencilcaseman@gmail.com
License: MIT Licences
Keywords: math,matrix,vector,network,neural network,libpymath,pymath,libmath,progress bar,progress
Platform: UNKNOWN
Classifier: Development Status :: 2 - Pre-Alpha
Classifier: Intended Audience :: Developers
Classifier: Intended Audience :: Education
Classifier: License :: OSI Approved :: MIT License
Classifier: Programming Language :: Python
Classifier: Programming Language :: Python :: 3.5
Classifier: Programming Language :: Python :: 3.6
Classifier: Programming Language :: Python :: 3.7
Classifier: Programming Language :: Python :: 3.8
Classifier: Programming Language :: Python :: 3.9
